digits/__init__.py
digits/digits.py
digits_py_lib-1.0.2.dist-info/LICENSE
digits_py_lib-1.0.2.dist-info/WHEEL
digits_py_lib-1.0.2.dist-info/METADATA
digits_py_lib-1.0.2.dist-info/RECORD
